django_simple_toc/__init__.py
django_simple_toc/apps.py
django_simple_toc/middleware.py
django_simple_toc/tests.py
django_simple_toc/migrations/__init__.py
django_simple_toc/templates/table-of-content-element.html
django_simple_toc/templates/table-of-content.html
django_simple_toc-0.0.3.dist-info/METADATA
django_simple_toc-0.0.3.dist-info/WHEEL
django_simple_toc-0.0.3.dist-info/licenses/LICENCE
django_simple_toc-0.0.3.dist-info/RECORD
